cloudydict
cloudydict/django_storage
cloudydict/common
cloudydict/cloudfiles
cloudydict/__init__
cloudydict/s3
