Metadata-Version: 1.0
Name: cloudydict
Version: 0.0.11
Summary: Dictionary interface to cloud providers.
Home-page: https://github.com/wnyc/cloudydict 
Author: Adam DePrince
Author-email: adeprince@nypublicradio.org
License: GPL
Platform: UNKNOWN
